{
  "data": {
    "article": {},
    "attachments": {
      "media_keys": [
        "3_2069829708091727872"
      ],
      "media_source_tweet_id": [
        "2069829717377818803"
      ]
    },
    "author_id": "1839085606573637632",
    "context_annotations": [
      {
        "domain": {
          "description": "Categories within Brand Verticals that narrow down the scope of Brands",
          "id": "46",
          "name": "Business Taxonomy"
        },
        "entity": {
          "description": "Brands, companies, advertisers and every non-person handle with the profit intent related to offline and online games such as gaming consoles, tabletop games, video game publishers",
          "id": "1557696940178935808",
          "name": "Gaming Business"
        }
      }
    ],
    "conversation_id": "2070005296903451043",
    "created_at": "2026-06-25T04:44:56.000Z",
    "edit_controls": {
      "editable_until": "2026-06-25T05:44:56.000Z",
      "edits_remaining": 5,
      "is_edit_eligible": false
    },
    "edit_history_tweet_ids": [
      "2070005296903451043"
    ],
    "entities": {
      "mentions": [
        {
          "end": 18,
          "id": "1599012090517540869",
          "start": 3,
          "username": "loveforeversfy"
        }
      ],
      "urls": [
        {
          "display_url": "pic.x.com/7tv3m50fj7",
          "end": 84,
          "expanded_url": "https://x.com/loveforeversfy/status/2069829717377818803/photo/1",
          "media_key": "3_2069829708091727872",
          "start": 61,
          "url": "https://t.co/7tv3m50fj7"
        }
      ]
    },
    "geo": {},
    "id": "2070005296903451043",
    "lang": "zh",
    "note_tweet": {
      "entities": {}
    },
    "possibly_sensitive": false,
    "public_metrics": {
      "bookmark_count": 0,
      "impression_count": 0,
      "like_count": 0,
      "quote_count": 0,
      "reply_count": 0,
      "retweet_count": 19
    },
    "referenced_tweets": [
      {
        "id": "2069829717377818803",
        "type": "retweeted"
      }
    ],
    "reply_settings": "everyone",
    "text": "RT @loveforeversfy: 2500fo纪念！！\n\n转发关注抽奖三盒玉米面五天后开奖（wohuineidin https://t.co/7tv3m50fj7"
  },
  "includes": {
    "media": [
      {
        "height": 1024,
        "media_key": "3_2069829708091727872",
        "public_metrics": {},
        "type": "photo",
        "url": "https://pbs.twimg.com/media/HLmDJzBboAAvl8_.jpg",
        "width": 977
      }
    ],
    "tweets": [
      {
        "article": {},
        "attachments": {
          "media_keys": [
            "3_2069829708091727872"
          ],
          "media_source_tweet_id": [
            "2069829717377818803"
          ]
        },
        "author_id": "1839085606573637632",
        "context_annotations": [
          {
            "domain": {
              "description": "Categories within Brand Verticals that narrow down the scope of Brands",
              "id": "46",
              "name": "Business Taxonomy"
            },
            "entity": {
              "description": "Brands, companies, advertisers and every non-person handle with the profit intent related to offline and online games such as gaming consoles, tabletop games, video game publishers",
              "id": "1557696940178935808",
              "name": "Gaming Business"
            }
          }
        ],
        "conversation_id": "2070005296903451043",
        "created_at": "2026-06-25T04:44:56.000Z",
        "edit_controls": {
          "editable_until": "2026-06-25T05:44:56.000Z",
          "edits_remaining": 5,
          "is_edit_eligible": false
        },
        "edit_history_tweet_ids": [
          "2070005296903451043"
        ],
        "entities": {
          "mentions": [
            {
              "end": 18,
              "id": "1599012090517540869",
              "start": 3,
              "username": "loveforeversfy"
            }
          ],
          "urls": [
            {
              "display_url": "pic.x.com/7tv3m50fj7",
              "end": 84,
              "expanded_url": "https://x.com/loveforeversfy/status/2069829717377818803/photo/1",
              "media_key": "3_2069829708091727872",
              "start": 61,
              "url": "https://t.co/7tv3m50fj7"
            }
          ]
        },
        "geo": {},
        "id": "2070005296903451043",
        "lang": "zh",
        "note_tweet": {
          "entities": {}
        },
        "possibly_sensitive": false,
        "public_metrics": {
          "bookmark_count": 0,
          "impression_count": 0,
          "like_count": 0,
          "quote_count": 0,
          "reply_count": 0,
          "retweet_count": 19
        },
        "referenced_tweets": [
          {
            "id": "2069829717377818803",
            "type": "retweeted"
          }
        ],
        "reply_settings": "everyone",
        "text": "RT @loveforeversfy: 2500fo纪念！！\n\n转发关注抽奖三盒玉米面五天后开奖（wohuineidin https://t.co/7tv3m50fj7"
      },
      {
        "article": {},
        "attachments": {
          "media_keys": [
            "3_2069829708091727872"
          ]
        },
        "author_id": "1599012090517540869",
        "context_annotations": [
          {
            "domain": {
              "description": "Categories within Brand Verticals that narrow down the scope of Brands",
              "id": "46",
              "name": "Business Taxonomy"
            },
            "entity": {
              "description": "Brands, companies, advertisers and every non-person handle with the profit intent related to offline and online games such as gaming consoles, tabletop games, video game publishers",
              "id": "1557696940178935808",
              "name": "Gaming Business"
            }
          }
        ],
        "conversation_id": "2069829717377818803",
        "created_at": "2026-06-24T17:07:14.000Z",
        "edit_controls": {
          "editable_until": "2026-06-24T18:07:14.000Z",
          "edits_remaining": 5,
          "is_edit_eligible": true
        },
        "edit_history_tweet_ids": [
          "2069829717377818803"
        ],
        "entities": {
          "urls": [
            {
              "display_url": "pic.x.com/7tv3m50fj7",
              "end": 64,
              "expanded_url": "https://x.com/loveforeversfy/status/2069829717377818803/photo/1",
              "media_key": "3_2069829708091727872",
              "start": 41,
              "url": "https://t.co/7tv3m50fj7"
            }
          ]
        },
        "geo": {},
        "id": "2069829717377818803",
        "lang": "zh",
        "note_tweet": {
          "entities": {}
        },
        "possibly_sensitive": false,
        "public_metrics": {
          "bookmark_count": 0,
          "impression_count": 1443,
          "like_count": 44,
          "quote_count": 0,
          "reply_count": 11,
          "retweet_count": 19
        },
        "reply_settings": "everyone",
        "text": "2500fo纪念！！\n\n转发关注抽奖三盒玉米面五天后开奖（wohuineidin https://t.co/7tv3m50fj7"
      }
    ],
    "users": [
      {
        "created_at": "2024-09-25T23:32:44.000Z",
        "description": "可以叫我之之丨生理心理皆女丨lgbtq友好丨我割我抽我o丨不鉴证丨喜欢互动 丨我没有🚪觉得我以后会在推上发点什么的不要关注我了丨只有绿色健康小清新🍀丨没有门不接线上不接线下没有非绿没有半绿没有纯绿丨\n防炸@LeeSong14176丨互fo直关丨没回fo私我",
        "entities": {
          "description": {
            "mentions": [
              {
                "end": 115,
                "start": 102,
                "username": "LeeSong14176"
              }
            ]
          }
        },
        "id": "1839085606573637632",
        "location": "蓝色宇宙",
        "name": "cafe114",
        "pinned_tweet_id": "2065050387967840395",
        "profile_image_url": "https://pbs.twimg.com/profile_images/2050427976786010112/u0ceyAKE_normal.jpg",
        "protected": false,
        "public_metrics": {
          "followers_count": 576,
          "following_count": 578,
          "like_count": 1301,
          "listed_count": 0,
          "media_count": 305,
          "tweet_count": 3301
        },
        "url": "",
        "username": "zhiii_tan",
        "verified": false
      },
      {
        "created_at": "2022-12-03T12:06:13.000Z",
        "description": "严重脑残｜enby｜🚪67",
        "id": "1599012090517540869",
        "name": "蘑菇盆栽🍄",
        "pinned_tweet_id": "2068997025849647511",
        "profile_image_url": "https://pbs.twimg.com/profile_images/2000518712626229248/-YPIFnC8_normal.jpg",
        "protected": false,
        "public_metrics": {
          "followers_count": 2529,
          "following_count": 1557,
          "like_count": 35338,
          "listed_count": 8,
          "media_count": 1213,
          "tweet_count": 11376
        },
        "url": "",
        "username": "loveforeversfy",
        "verified": false
      }
    ]
  }
}