{
  "data": {
    "article": {},
    "attachments": {},
    "author_id": "1839085606573637632",
    "conversation_id": "2064039971884077189",
    "created_at": "2026-06-08T19:33:41.000Z",
    "edit_controls": {
      "editable_until": "2026-06-08T20:33:41.000Z",
      "edits_remaining": 5,
      "is_edit_eligible": false
    },
    "edit_history_tweet_ids": [
      "2064068365388599449"
    ],
    "entities": {
      "mentions": [
        {
          "end": 13,
          "id": "2053366838248259584",
          "start": 0,
          "username": "Cassie2meqwq"
        }
      ]
    },
    "geo": {},
    "id": "2064068365388599449",
    "in_reply_to_user_id": "2053366838248259584",
    "lang": "zh",
    "note_tweet": {
      "entities": {}
    },
    "possibly_sensitive": false,
    "public_metrics": {
      "bookmark_count": 0,
      "impression_count": 0,
      "like_count": 0,
      "quote_count": 0,
      "reply_count": 0,
      "retweet_count": 0
    },
    "referenced_tweets": [
      {
        "id": "2064066193577922598",
        "type": "replied_to"
      }
    ],
    "reply_settings": "everyone",
    "text": "@Cassie2meqwq 喜欢春天！一直在坚持的事我要想想，超话签到，永远对世界保持温柔，包容的看待\n我没什么坚持的东西😨😭\n喜欢春天是因为是新一年的开始，希望我的人生能像春天一样拥有新的开始，出现新的事物等待我去体验，而且春天很舒服"
  },
  "includes": {
    "tweets": [
      {
        "article": {},
        "attachments": {},
        "author_id": "1839085606573637632",
        "conversation_id": "2064039971884077189",
        "created_at": "2026-06-08T19:33:41.000Z",
        "edit_controls": {
          "editable_until": "2026-06-08T20:33:41.000Z",
          "edits_remaining": 5,
          "is_edit_eligible": false
        },
        "edit_history_tweet_ids": [
          "2064068365388599449"
        ],
        "entities": {
          "mentions": [
            {
              "end": 13,
              "id": "2053366838248259584",
              "start": 0,
              "username": "Cassie2meqwq"
            }
          ]
        },
        "geo": {},
        "id": "2064068365388599449",
        "in_reply_to_user_id": "2053366838248259584",
        "lang": "zh",
        "note_tweet": {
          "entities": {}
        },
        "possibly_sensitive": false,
        "public_metrics": {
          "bookmark_count": 0,
          "impression_count": 0,
          "like_count": 0,
          "quote_count": 0,
          "reply_count": 0,
          "retweet_count": 0
        },
        "referenced_tweets": [
          {
            "id": "2064066193577922598",
            "type": "replied_to"
          }
        ],
        "reply_settings": "everyone",
        "text": "@Cassie2meqwq 喜欢春天！一直在坚持的事我要想想，超话签到，永远对世界保持温柔，包容的看待\n我没什么坚持的东西😨😭\n喜欢春天是因为是新一年的开始，希望我的人生能像春天一样拥有新的开始，出现新的事物等待我去体验，而且春天很舒服"
      },
      {
        "article": {},
        "attachments": {},
        "author_id": "2053366838248259584",
        "conversation_id": "2064039971884077189",
        "created_at": "2026-06-08T19:25:03.000Z",
        "edit_controls": {
          "editable_until": "2026-06-08T20:25:03.000Z",
          "edits_remaining": 5,
          "is_edit_eligible": false
        },
        "edit_history_tweet_ids": [
          "2064066193577922598"
        ],
        "entities": {
          "mentions": [
            {
              "end": 10,
              "id": "1839085606573637632",
              "start": 0,
              "username": "zhiii_tan"
            }
          ]
        },
        "geo": {},
        "id": "2064066193577922598",
        "in_reply_to_user_id": "1839085606573637632",
        "lang": "ja",
        "note_tweet": {
          "entities": {}
        },
        "possibly_sensitive": false,
        "public_metrics": {
          "bookmark_count": 0,
          "impression_count": 3,
          "like_count": 0,
          "quote_count": 0,
          "reply_count": 1,
          "retweet_count": 0
        },
        "referenced_tweets": [
          {
            "id": "2064039971884077189",
            "type": "replied_to"
          }
        ],
        "reply_settings": "everyone",
        "text": "@zhiii_tan 55和7😋"
      }
    ],
    "users": [
      {
        "created_at": "2024-09-25T23:32:44.000Z",
        "description": "可以叫我之之/生理心理皆女/lgbtq友好/泛性恋/我割我抽我o/od持开放态度 不一定碰但是不会反感 不鉴证 喜欢萌妹子 某些男的想加我先v520  我没有🚪觉得我以后会在推上发点什么的不要关注我了还是 只有绿色健康小清新🍀\n世界上的另一个我@LeeSong14176",
        "entities": {
          "description": {
            "mentions": [
              {
                "end": 135,
                "start": 122,
                "username": "LeeSong14176"
              }
            ]
          }
        },
        "id": "1839085606573637632",
        "location": "蓝色宇宙",
        "name": "cafe114",
        "pinned_tweet_id": "2064034397750464763",
        "profile_image_url": "https://pbs.twimg.com/profile_images/2050427976786010112/u0ceyAKE_normal.jpg",
        "protected": false,
        "public_metrics": {
          "followers_count": 410,
          "following_count": 435,
          "like_count": 994,
          "listed_count": 0,
          "media_count": 176,
          "tweet_count": 2373
        },
        "username": "zhiii_tan",
        "verified": false
      },
      {
        "created_at": "2026-05-10T06:50:59.000Z",
        "description": "因为爱存在\n| 已成年| BD | OVERDOSE | BISEXUAL | 文青病｜语言是 中韩英|查成分互fo",
        "id": "2053366838248259584",
        "name": "酸性✝️",
        "pinned_tweet_id": "2057485786535313415",
        "profile_image_url": "https://pbs.twimg.com/profile_images/2057427639531638786/4bR3vvpl_normal.jpg",
        "protected": false,
        "public_metrics": {
          "followers_count": 220,
          "following_count": 207,
          "like_count": 242,
          "listed_count": 0,
          "media_count": 21,
          "tweet_count": 492
        },
        "username": "Cassie2meqwq",
        "verified": false
      }
    ]
  }
}