{
  "data": {
    "article": {},
    "attachments": {},
    "author_id": "1839085606573637632",
    "conversation_id": "2070765482765070827",
    "created_at": "2026-06-27T07:05:38.000Z",
    "edit_controls": {
      "editable_until": "2026-06-27T08:05:38.000Z",
      "edits_remaining": 5,
      "is_edit_eligible": false
    },
    "edit_history_tweet_ids": [
      "2070765482765070827"
    ],
    "entities": {
      "mentions": [
        {
          "end": 12,
          "id": "1157510978684121088",
          "start": 3,
          "username": "yangcier"
        },
        {
          "end": 25,
          "id": "1756909109788753920",
          "start": 14,
          "username": "__fanqie__"
        }
      ]
    },
    "geo": {},
    "id": "2070765482765070827",
    "lang": "zh",
    "note_tweet": {
      "entities": {}
    },
    "possibly_sensitive": false,
    "public_metrics": {
      "bookmark_count": 0,
      "impression_count": 0,
      "like_count": 0,
      "quote_count": 0,
      "reply_count": 0,
      "retweet_count": 15
    },
    "referenced_tweets": [
      {
        "id": "2070219933968224754",
        "type": "retweeted"
      }
    ],
    "reply_settings": "everyone",
    "text": "RT @yangcier: @__fanqie__ 都跑外网来了这五个b还在追我我真没招了"
  },
  "includes": {
    "tweets": [
      {
        "article": {},
        "attachments": {},
        "author_id": "1839085606573637632",
        "conversation_id": "2070765482765070827",
        "created_at": "2026-06-27T07:05:38.000Z",
        "edit_controls": {
          "editable_until": "2026-06-27T08:05:38.000Z",
          "edits_remaining": 5,
          "is_edit_eligible": false
        },
        "edit_history_tweet_ids": [
          "2070765482765070827"
        ],
        "entities": {
          "mentions": [
            {
              "end": 12,
              "id": "1157510978684121088",
              "start": 3,
              "username": "yangcier"
            },
            {
              "end": 25,
              "id": "1756909109788753920",
              "start": 14,
              "username": "__fanqie__"
            }
          ]
        },
        "geo": {},
        "id": "2070765482765070827",
        "lang": "zh",
        "note_tweet": {
          "entities": {}
        },
        "possibly_sensitive": false,
        "public_metrics": {
          "bookmark_count": 0,
          "impression_count": 0,
          "like_count": 0,
          "quote_count": 0,
          "reply_count": 0,
          "retweet_count": 15
        },
        "referenced_tweets": [
          {
            "id": "2070219933968224754",
            "type": "retweeted"
          }
        ],
        "reply_settings": "everyone",
        "text": "RT @yangcier: @__fanqie__ 都跑外网来了这五个b还在追我我真没招了"
      },
      {
        "article": {},
        "attachments": {},
        "author_id": "1157510978684121088",
        "conversation_id": "2070101892479504537",
        "created_at": "2026-06-25T18:57:49.000Z",
        "edit_controls": {
          "editable_until": "2026-06-25T19:57:49.000Z",
          "edits_remaining": 5,
          "is_edit_eligible": false
        },
        "edit_history_tweet_ids": [
          "2070219933968224754"
        ],
        "entities": {
          "mentions": [
            {
              "end": 11,
              "id": "1756909109788753920",
              "start": 0,
              "username": "__fanqie__"
            }
          ]
        },
        "geo": {},
        "id": "2070219933968224754",
        "in_reply_to_user_id": "1756909109788753920",
        "lang": "zh",
        "note_tweet": {
          "entities": {}
        },
        "possibly_sensitive": false,
        "public_metrics": {
          "bookmark_count": 1,
          "impression_count": 105662,
          "like_count": 1887,
          "quote_count": 2,
          "reply_count": 3,
          "retweet_count": 15
        },
        "referenced_tweets": [
          {
            "id": "2070101892479504537",
            "type": "replied_to"
          }
        ],
        "reply_settings": "everyone",
        "text": "@__fanqie__ 都跑外网来了这五个b还在追我我真没招了"
      }
    ],
    "users": [
      {
        "created_at": "2024-09-25T23:32:44.000Z",
        "description": "可以叫我之之丨生理心理皆女丨lgbtq友好丨我割我抽我o丨不鉴证丨喜欢互动 丨我没有🚪觉得我以后会在推上发点什么的不要关注我了丨只有绿色健康小清新🍀丨没有门不接线上不接线下没有非绿没有半绿没有纯绿丨\n防炸@LeeSong14176丨互fo直关丨没回fo私我",
        "entities": {
          "description": {
            "mentions": [
              {
                "end": 115,
                "start": 102,
                "username": "LeeSong14176"
              }
            ]
          }
        },
        "id": "1839085606573637632",
        "location": "蓝色宇宙",
        "name": "cafe114",
        "pinned_tweet_id": "2065050387967840395",
        "profile_image_url": "https://pbs.twimg.com/profile_images/2050427976786010112/u0ceyAKE_normal.jpg",
        "protected": false,
        "public_metrics": {
          "followers_count": 576,
          "following_count": 580,
          "like_count": 1344,
          "listed_count": 0,
          "media_count": 311,
          "tweet_count": 3344
        },
        "url": "",
        "username": "zhiii_tan",
        "verified": false
      },
      {
        "created_at": "2019-08-03T04:38:17.000Z",
        "description": "💜BTS NCT KATSEYE LNGSHOT💚\n\n💛DeadbyDaylight-JiwoonHak💛\n\n💚OC-柳关河🩵",
        "id": "1157510978684121088",
        "name": "yangcier",
        "profile_image_url": "https://pbs.twimg.com/profile_images/2050117570938970112/xP-YYvoM_normal.jpg",
        "protected": false,
        "public_metrics": {
          "followers_count": 4,
          "following_count": 118,
          "like_count": 857,
          "listed_count": 0,
          "media_count": 12,
          "tweet_count": 348
        },
        "url": "",
        "username": "yangcier",
        "verified": false
      },
      {
        "created_at": "2024-02-12T05:12:40.000Z",
        "description": "这里是番茄🍅随机性评论\n不讨论政治/随缘分享\n侵权私信删除/接受投稿\n评论区约炮广告均为诈骗，请勿相信",
        "id": "1756909109788753920",
        "location": "番茄树上",
        "name": "不包番茄籽的番茄",
        "pinned_tweet_id": "2070371593738661970",
        "profile_image_url": "https://pbs.twimg.com/profile_images/2043538335155859456/EL2nafA__normal.jpg",
        "protected": false,
        "public_metrics": {
          "followers_count": 9090,
          "following_count": 2779,
          "like_count": 1597,
          "listed_count": 18,
          "media_count": 1937,
          "tweet_count": 10446
        },
        "url": "",
        "username": "__fanqie__",
        "verified": true
      }
    ]
  }
}